sdynpy/__init__.py
sdynpy/core/GUIPlot.ui
sdynpy/core/__init__.py
sdynpy/core/sdynpy_array.py
sdynpy/core/sdynpy_colors.py
sdynpy/core/sdynpy_coordinate.py
sdynpy/core/sdynpy_data.py
sdynpy/core/sdynpy_geometry.py
sdynpy/core/sdynpy_matrix.py
sdynpy/core/sdynpy_shape.py
sdynpy/core/sdynpy_system.py
sdynpy/demo/__init__.py
sdynpy/demo/beam_airplane.py
sdynpy/demo/beam_plate.py
sdynpy/doc/__init__.py
sdynpy/doc/sdynpy_latex.py
sdynpy/doc/sdynpy_ppt.py
sdynpy/fem/__init__.py
sdynpy/fem/sdynpy_beam.py
sdynpy/fem/sdynpy_dof.py
sdynpy/fem/sdynpy_exodus.py
sdynpy/fem/sdynpy_shaker.py
sdynpy/fileio/__init__.py
sdynpy/fileio/escdf_visualizer.ui
sdynpy/fileio/sdynpy_dataphysics.py
sdynpy/fileio/sdynpy_escdf.py
sdynpy/fileio/sdynpy_pdf3D.py
sdynpy/fileio/sdynpy_rattlesnake.py
sdynpy/fileio/sdynpy_tshaker.py
sdynpy/fileio/sdynpy_uff.py
sdynpy/fileio/sdynpy_vic.py
sdynpy/fileio/sdynpy_uff_datasets/__init__.py
sdynpy/fileio/sdynpy_uff_datasets/sdynpy_uff_dataset_151.py
sdynpy/fileio/sdynpy_uff_datasets/sdynpy_uff_dataset_164.py
sdynpy/fileio/sdynpy_uff_datasets/sdynpy_uff_dataset_1858.py
sdynpy/fileio/sdynpy_uff_datasets/sdynpy_uff_dataset_2400.py
sdynpy/fileio/sdynpy_uff_datasets/sdynpy_uff_dataset_2411.py
sdynpy/fileio/sdynpy_uff_datasets/sdynpy_uff_dataset_2412.py
sdynpy/fileio/sdynpy_uff_datasets/sdynpy_uff_dataset_2420.py
sdynpy/fileio/sdynpy_uff_datasets/sdynpy_uff_dataset_55.py
sdynpy/fileio/sdynpy_uff_datasets/sdynpy_uff_dataset_58.py
sdynpy/fileio/sdynpy_uff_datasets/sdynpy_uff_dataset_82.py
sdynpy/modal/__init__.py
sdynpy/modal/colored_cmif.ui
sdynpy/modal/mode_properties.ui
sdynpy/modal/polypy.ui
sdynpy/modal/polypy_stability_diagram.ui
sdynpy/modal/sdynpy_ccmif.py
sdynpy/modal/sdynpy_modal_test.py
sdynpy/modal/sdynpy_modeshape.py
sdynpy/modal/sdynpy_polypy.py
sdynpy/modal/sdynpy_signal_processing_gui.py
sdynpy/modal/sdynpy_smac.py
sdynpy/modal/signal_processing.ui
sdynpy/modal/smac.ui
sdynpy/modal/smac_add_root.ui
sdynpy/signal_processing/__init__.py
sdynpy-0.19.0.dist-info/licenses/LICENSE
sdynpy-0.19.0.dist-info/METADATA
sdynpy-0.19.0.dist-info/WHEEL
sdynpy-0.19.0.dist-info/top_level.txt
sdynpy-0.19.0.dist-info/RECORD
