Metadata-Version: 2.4
Name: sdynpy
Version: 0.19.0
Summary: A Structural Dynamics Library for Python
Author: Daniel P. Rohe
Author-email: dprohe@sandia.gov
License: Copyright 2022 National Technology & Engineering Solutions of Sandia, LLC
Project-URL: Documentation, http://structmechtools.cee-gitlab.lan/structural-dynamics-python-libraries/
Project-URL: Repository, https://cee-gitlab.sandia.gov/structMechTools/structural-dynamics-python-libraries
Classifier: Natural Language :: English
Classifier: Operating System :: Microsoft :: Windows :: Windows 10
Classifier: Operating System :: MacOS :: MacOS X
Classifier: Operating System :: POSIX :: Linux
Classifier: Programming Language :: Python :: 3.10
Classifier: Framework :: Pytest
Classifier: License :: OSI Approved :: GNU General Public License v3 (GPLv3)
Requires-Python: >=3.10
License-File: LICENSE
Requires-Dist: numpy
Requires-Dist: scipy
Requires-Dist: matplotlib
Requires-Dist: qtpy
Requires-Dist: PyQt5
Requires-Dist: pyqtgraph
Requires-Dist: netCDF4
Requires-Dist: pandas
Requires-Dist: python-pptx
Requires-Dist: Pillow
Requires-Dist: pyvista
Requires-Dist: pyvistaqt
Requires-Dist: openpyxl
Requires-Dist: vtk
Requires-Dist: h5py
Provides-Extra: lrm
Requires-Dist: joblib; extra == "lrm"
Requires-Dist: psutils; extra == "lrm"
Provides-Extra: pdf3d
Requires-Dist: vtk-u3dexporter; extra == "pdf3d"
Provides-Extra: tshaker
Requires-Dist: npTDMS; extra == "tshaker"
Provides-Extra: docs
Requires-Dist: docutils<0.18,>=0.14; extra == "docs"
Requires-Dist: ipykernel; extra == "docs"
Requires-Dist: ipython; extra == "docs"
Requires-Dist: jinja2>=3.0; extra == "docs"
Requires-Dist: nbsphinx; extra == "docs"
Requires-Dist: sphinx; extra == "docs"
Requires-Dist: sphinx-rtd-theme; extra == "docs"
Requires-Dist: sphinxcontrib-bibtex; extra == "docs"
Requires-Dist: sphinx-copybutton; extra == "docs"
Provides-Extra: testing
Requires-Dist: pytest; extra == "testing"
Requires-Dist: pytest-cov; extra == "testing"
Requires-Dist: coverage; extra == "testing"
Provides-Extra: all
Requires-Dist: docutils<0.18,>=0.14; extra == "all"
Requires-Dist: ipykernel; extra == "all"
Requires-Dist: ipython; extra == "all"
Requires-Dist: jinja2>=3.0; extra == "all"
Requires-Dist: nbsphinx; extra == "all"
Requires-Dist: pytest; extra == "all"
Requires-Dist: coverage; extra == "all"
Requires-Dist: pytest-cov; extra == "all"
Requires-Dist: sphinx; extra == "all"
Requires-Dist: sphinx-rtd-theme; extra == "all"
Requires-Dist: sphinxcontrib-bibtex; extra == "all"
Requires-Dist: sphinx-copybutton; extra == "all"
Dynamic: license-file
